pyC4Room/__init__.py
pyC4Room/account.py
pyC4Room/alarm.py
pyC4Room/blind.py
pyC4Room/director.py
pyC4Room/error_handling.py
pyC4Room/light.py
pyC4Room/relay.py
pyC4Room/room.py
pyC4Room/websocket.py
pyControl4/__init__.py
pyControl4/account.py
pyControl4/alarm.py
pyControl4/blind.py
pyControl4/director.py
pyControl4/error_handling.py
pyControl4/light.py
pyControl4/relay.py
pyControl4/room.py
pyControl4/websocket.py
pyControl4Room/__init__.py
pyControl4Room/account.py
pyControl4Room/alarm.py
pyControl4Room/blind.py
pyControl4Room/director.py
pyControl4Room/error_handling.py
pyControl4Room/light.py
pyControl4Room/relay.py
pyControl4Room/room.py
pyControl4Room/websocket.py
pyC4Room-1.0.0.dist-info/LICENSE
pyC4Room-1.0.0.dist-info/METADATA
pyC4Room-1.0.0.dist-info/WHEEL
pyC4Room-1.0.0.dist-info/top_level.txt
pyC4Room-1.0.0.dist-info/RECORD
